com/__init__.py
com/precisely/__init__.py
com/precisely/apis/__init__.py
com/precisely/apis/api_client.py
com/precisely/apis/configuration.py
com/precisely/apis/exceptions.py
com/precisely/apis/model_utils.py
com/precisely/apis/rest.py
com/precisely/apis/api/__init__.py
com/precisely/apis/api/address_autocomplete_enterprise_service_api.py
com/precisely/apis/api/address_autocomplete_service_api.py
com/precisely/apis/api/address_verification_service_api.py
com/precisely/apis/api/addresses_service__api.py
com/precisely/apis/api/demographics_service_api.py
com/precisely/apis/api/email_verification_service_api.py
com/precisely/apis/api/geocode_service_api.py
com/precisely/apis/api/geolocation_service_api.py
com/precisely/apis/api/local_tax_service_api.py
com/precisely/apis/api/neighborhoods_service__api.py
com/precisely/apis/api/phone_verification_service_api.py
com/precisely/apis/api/places_service__api.py
com/precisely/apis/api/property_information_service_api.py
com/precisely/apis/api/psap_911_service_api.py
com/precisely/apis/api/risks_service_api.py
com/precisely/apis/api/routing_service_api.py
com/precisely/apis/api/schools_service_api.py
com/precisely/apis/api/streets_service_api.py
com/precisely/apis/api/telecomm_info_service_api.py
com/precisely/apis/api/time_zone_service_api.py
com/precisely/apis/api/zones_service_api.py
com/precisely/apis/apis/__init__.py
com/precisely/apis/model/__init__.py
com/precisely/apis/model/absentee_owner.py
com/precisely/apis/model/accuracy.py
com/precisely/apis/model/address.py
com/precisely/apis/model/address1.py
com/precisely/apis/model/address2.py
com/precisely/apis/model/address_time.py
com/precisely/apis/model/address_type.py
com/precisely/apis/model/addresses_by_boundary_request.py
com/precisely/apis/model/addresses_count.py
com/precisely/apis/model/addresses_dto.py
com/precisely/apis/model/addresses_preferences.py
com/precisely/apis/model/addresses_response.py
com/precisely/apis/model/ah_jmailing_address.py
com.precisely.apis-18.1.1.dist-info/LICENSE
com.precisely.apis-18.1.1.dist-info/METADATA
com.precisely.apis-18.1.1.dist-info/WHEEL
com.precisely.apis-18.1.1.dist-info/top_level.txt
com.precisely.apis-18.1.1.dist-info/RECORD
