Metadata-Version: 2.1
Name: com.precisely.apis
Version: 18.1.1
Summary: Precisely APIs
Home-page: https://developer.precisely.com/
Author: Precisely APIs Support
Author-email: PreciselyAPIs-Support@precisely.com
License: Apache 2.0
Keywords: Precisely APIs
Requires-Python: >=3.6
License-File: LICENSE
Requires-Dist: urllib3 >=1.25.3
Requires-Dist: python-dateutil
Requires-Dist: requests
